{
    "lanes": {
        "count": 4,
        "types": ["S", "D", "S", "D"]
    },
    "waves": [
        {
            "numA": 2,
            "numB_Safe": 1,
            "numB_Danger": 1,
            "numC": 1
        },
        {
            "numA": 1,
            "numB_Safe": 2,
            "numB_Danger": 2,
            "numC": 2
        }
    ],
    "scanners": [
        {
            "lane":0,
            "y":400
        },
        {
            "lane":2,
            "y":700
        }
    ],
    "starThresholds": [10, 2, 0]
}